Server/__init__.py
Server/__main__.py
Server/application.py
Server/configuration.py
server_unite-0.0.7.dist-info/METADATA
server_unite-0.0.7.dist-info/WHEEL
server_unite-0.0.7.dist-info/entry_points.txt
server_unite-0.0.7.dist-info/licenses/LICENSE
server_unite-0.0.7.dist-info/RECORD
