Metadata-Version: 2.4
Name: server-unite
Version: 0.0.7
Summary: Manage server deployments
Project-URL: Homepage, https://gitlab.com/0tanay/server
Project-URL: Repository, https://gitlab.com/0tanay/server.git
Project-URL: Issues, https://gitlab.com/0tanay/server/-/issues
License-File: LICENSE
Requires-Dist: click
Requires-Dist: docker-unite
Requires-Dist: git-unite
Requires-Dist: pyyaml
